langsnapy/__init__.py
langsnapy/_output_format.py
langsnapy/compare_results.py
langsnapy/langchain.py
langsnapy/project.py
langsnapy/snapshot.py
langsnapy-0.0.4.dist-info/LICENSE
langsnapy-0.0.4.dist-info/METADATA
langsnapy-0.0.4.dist-info/WHEEL
langsnapy-0.0.4.dist-info/RECORD
