Metadata-Version: 2.1
Name: langsnapy
Version: 0.0.4
Summary: Snapshot your LLMs, NLP and Chatbots
Author: Mykhailo Chalyi
Author-email: mike@chaliy.name
Requires-Python: >=3.11,<4.0
Classifier: Programming Language :: Python :: 3
Classifier: Programming Language :: Python :: 3.11
Classifier: Programming Language :: Python :: 3.12
Provides-Extra: runtime-deps
Requires-Dist: dataclasses-json (>=0.6.3,<0.7.0)
Requires-Dist: markdown-it-py (>=3.0.0,<4.0.0) ; extra == "runtime-deps"
Requires-Dist: pyyaml (>=6.0.1,<7.0.0)
